{"forks_count":35,"forkers":["NODE2C","pandepardhasaradhi","spinochenza","rajivraj","syntaxHax","mainuddinroyal","Rxlandas","Outs1d3r-Net","altanateser","0xSojalSec","sidneysimas","marcostolosa","UCL-AC","awanvenom","nak000","UncleJ4ck","Belebez","Sy3Omda","lastnameradeon","emdnaia","bbbfkl","samy4samy","gmh5225","killvxk","opoet7","gibbop9","nowu354","Shadowroot97","R4PO","naitsirhc41","mguelcl","symbiotik007","PatrickSec","Fr4nzisko"],"stargazers_count":208,"stargazers":["TaurusOmar","Gaurav1020","injcristianrojas","secjo","PatrickSec","xf0mar","r1nzleer","mguelcl","wulfrano","Blokui","heavyscan","y0k4i-1337","DictaDank","aacunaa","ELMERIKH","nullsecX270","duty9527","Titounkle","nrojas","mrpnkt","a-fallahi","Nyx2022","Shadowroot97","x0pr4nt3s","vay3t","Taius","d3ndr1t30x","J1mX","zero77","matbilodeau","CicadaMikoto","scmanjarrez","xrkk","Onismon","Saltinbank-SyS","RmFrZU90aGVycyEK","opoet7","Karm78","Mrhax0rr","ludothegreat","RojxPy","Scarther","cymilad","changheluor007","roj1py","killvxk","kernel-sanders","4mazing","Zubairkings","presianbg","QMSPS","kocurc","gman0x00","stultitiophobia","cmprmsd","shreethaar","lhhkujgnfb","th3g3ntl3m4n84","me009","keskinonur","Unkn0wnCreator","secfb","bigmangfu","startagain2016","zcbxxx1","bbbfkl","thelittlefireman","yrjo","MuzukashiMkJin","OffensiveBrute","habib26-14","0xsyr0","natesubra","hyperware1337","PaulzePirate","assarbad","lastnameradeon","jcdex69","flyingllama87","ciaran-finnegan","AZEC0x00","blupblob","favoritetechbrr","ettorhake","Spez77777","ergikruja","MaxToffy","MelForze","SantaLaMuerte","Veids","florianamette","SpadesA99","0xKingPin","keyb0rdvik1ng","HudsonSeiler","lzzbb","red2sol","tmcr00ze","san6051","drunkerone","arch3rPro","geeeeekcoooder","BilalGns","AAArenas","0x023","m0ng3sh3ll","Fr4nzisko","zhourong245","Fkdkutrfc","BorjaMerino","UncleJ4ck","HelixNewton","Und3rTakerOPS","zzryn","XLST-Qemu","Edov","elohffa","GillesSchippers","YukaFake","Codekies","mxvirus117","jamaal001","MarkoGordic","CesarBalzer","SonofaRN","ilker52","akamimuraf","dzygann","sh4hin","bidhata","sechvn","a7t0fwa7","frostydawg","ReB0rnzz","mochabyte0x","ZeroPing01","Outs1d3r-Net","xzxxzzzz000","keeganparr1","koztkozt","libearrrr","XZ00Z","Acemampz","nickvourd","shantanu561993","blake774D","chennqqi","AssassinUKG","crazyworlds","johdcyber","The-Viper-One","fckoo","pocppt","Anirudhx7","shrek3n","ToonExodia","MortexAG","xiaotsai","N0rdicSec","chrisbensch","cmndcntrlcyber","mpn","congtrung2k1","AkechiShiro","hazim-arbas","sadhuroot","WilleLX1","thestar0","st3rven","tanaka-geek","xLRST","wy876","wivd","her3ticAVI","Rablidad","Mrwithnomoney","pandepardhasaradhi","spoooky762","Xcution3r","qu4ngnm","SpeerSec","patrickt2017","LordCasser","ravindu644","exe-keppler","NODE2C","dur4ng","ger008","c0nfig-17","DouglasRao","Czr-Xploit","Chainski","0xDezzy","LUCIF3RX","jud3ns0hn","oyewunmio","redmanjacha","sugardaddy2020","EndlssNightmare","AronnaxM","UuF4bY","chiefspecialk","eforentropy","J0nasP","bob-reis","rewledp","Sir4h","zakr4k"],"watchers_count":208,"watchers":["TaurusOmar","Gaurav1020","injcristianrojas","secjo","PatrickSec","xf0mar","r1nzleer","mguelcl","wulfrano","Blokui","heavyscan","y0k4i-1337","DictaDank","aacunaa","ELMERIKH","nullsecX270","duty9527","Titounkle","nrojas","mrpnkt","a-fallahi","Nyx2022","Shadowroot97","x0pr4nt3s","vay3t","Taius","d3ndr1t30x","J1mX","zero77","matbilodeau","CicadaMikoto","scmanjarrez","xrkk","Onismon","Saltinbank-SyS","RmFrZU90aGVycyEK","opoet7","Karm78","Mrhax0rr","ludothegreat","RojxPy","Scarther","cymilad","changheluor007","roj1py","killvxk","kernel-sanders","4mazing","Zubairkings","presianbg","QMSPS","kocurc","gman0x00","stultitiophobia","cmprmsd","shreethaar","lhhkujgnfb","th3g3ntl3m4n84","me009","keskinonur","Unkn0wnCreator","secfb","bigmangfu","startagain2016","zcbxxx1","bbbfkl","thelittlefireman","yrjo","MuzukashiMkJin","OffensiveBrute","habib26-14","0xsyr0","natesubra","hyperware1337","PaulzePirate","assarbad","lastnameradeon","jcdex69","flyingllama87","ciaran-finnegan","AZEC0x00","blupblob","favoritetechbrr","ettorhake","Spez77777","ergikruja","MaxToffy","MelForze","SantaLaMuerte","Veids","florianamette","SpadesA99","0xKingPin","keyb0rdvik1ng","HudsonSeiler","lzzbb","red2sol","tmcr00ze","san6051","drunkerone","arch3rPro","geeeeekcoooder","BilalGns","AAArenas","0x023","m0ng3sh3ll","Fr4nzisko","zhourong245","Fkdkutrfc","BorjaMerino","UncleJ4ck","HelixNewton","Und3rTakerOPS","zzryn","XLST-Qemu","Edov","elohffa","GillesSchippers","YukaFake","Codekies","mxvirus117","jamaal001","MarkoGordic","CesarBalzer","SonofaRN","ilker52","akamimuraf","dzygann","sh4hin","bidhata","sechvn","a7t0fwa7","frostydawg","ReB0rnzz","mochabyte0x","ZeroPing01","Outs1d3r-Net","xzxxzzzz000","keeganparr1","koztkozt","libearrrr","XZ00Z","Acemampz","nickvourd","shantanu561993","blake774D","chennqqi","AssassinUKG","crazyworlds","johdcyber","The-Viper-One","fckoo","pocppt","Anirudhx7","shrek3n","ToonExodia","MortexAG","xiaotsai","N0rdicSec","chrisbensch","cmndcntrlcyber","mpn","congtrung2k1","AkechiShiro","hazim-arbas","sadhuroot","WilleLX1","thestar0","st3rven","tanaka-geek","xLRST","wy876","wivd","her3ticAVI","Rablidad","Mrwithnomoney","pandepardhasaradhi","spoooky762","Xcution3r","qu4ngnm","SpeerSec","patrickt2017","LordCasser","ravindu644","exe-keppler","NODE2C","dur4ng","ger008","c0nfig-17","DouglasRao","Czr-Xploit","Chainski","0xDezzy","LUCIF3RX","jud3ns0hn","oyewunmio","redmanjacha","sugardaddy2020","EndlssNightmare","AronnaxM","UuF4bY","chiefspecialk","eforentropy","J0nasP","bob-reis","rewledp","Sir4h","zakr4k"],"contributor_count":1,"contributors":["TaurusOmar"],"open_pull_request_count":0,"open_pull_requests":[],"label_count":9,"labels":["bug","documentation","duplicate","enhancement","good first issue","help wanted","invalid","question","wontfix"],"subscribers":["TaurusOmar","rikosintie","favoritetechbrr","ettorhake"],"subscribers_count":4,"committers":["web-flow","web-flow","web-flow","web-flow","web-flow","web-flow","web-flow"],"committers_count":1,"committers_emails":["xf0@xf0.xf0","xf0@xf0.xf0","xf0@xf0.xf0","xf0@xf0.xf0","xf0@xf0.xf0","xf0@xf0.xf0","xf0@xf0.xf0","xf0@xf0.xf0","xf0@xf0.xf0","xf0@xf0.xf0","xf0@xf0.xf0","xf0@xf0.xf0","xf0@xf0.xf0","xf0@xf0.xf0","72287837+TaurusOmar@users.noreply.github.com","72287837+TaurusOmar@users.noreply.github.com","72287837+TaurusOmar@users.noreply.github.com","72287837+TaurusOmar@users.noreply.github.com","72287837+TaurusOmar@users.noreply.github.com","72287837+TaurusOmar@users.noreply.github.com","72287837+TaurusOmar@users.noreply.github.com"],"committers_emails_count":2,"authors":["TaurusOmar","TaurusOmar","TaurusOmar","TaurusOmar","TaurusOmar","TaurusOmar","TaurusOmar"],"authors_count":1,"assignees":["TaurusOmar"],"assignees_count":1}